sample/part1.py
sample_pipeline-0.1.0.dist-info/METADATA
sample_pipeline-0.1.0.dist-info/WHEEL
sample_pipeline-0.1.0.dist-info/RECORD
